createflask/__init__.py
createflask/createapp.py
flask-createapp/__init__.py
flask-createapp/flask_create.py
createflask-1.7.5.dist-info/LICENSE
createflask-1.7.5.dist-info/METADATA
createflask-1.7.5.dist-info/WHEEL
createflask-1.7.5.dist-info/top_level.txt
createflask-1.7.5.dist-info/RECORD
