Metadata-Version: 2.1
Name: createflask
Version: 1.7.5
Summary: Python package for creating flaskapp
Home-page: UNKNOWN
Author: Throttlerz (Siddhartha Roy)
Author-email: <sid86harth@gmail.com>
License: UNKNOWN
Keywords: python,web development,createapp,automation,flask,python flask
Platform: UNKNOWN
Classifier: Development Status :: 1 - Planning
Classifier: Intended Audience :: Developers
Classifier: Programming Language :: Python :: 3
Classifier: Operating System :: Unix
Classifier: Operating System :: MacOS :: MacOS X
Classifier: Operating System :: Microsoft :: Windows
License-File: LICENSE
Requires-Dist: rich
